dictones/.git/COMMIT_EDITMSG
dictones/.git/config
dictones/.git/description
dictones/.git/HEAD
dictones/.git/hooks/applypatch-msg.sample
dictones/.git/hooks/commit-msg.sample
dictones/.git/hooks/fsmonitor-watchman.sample
dictones/.git/hooks/post-update.sample
dictones/.git/hooks/pre-applypatch.sample
dictones/.git/hooks/pre-commit.sample
dictones/.git/hooks/pre-merge-commit.sample
dictones/.git/hooks/pre-push.sample
dictones/.git/hooks/pre-rebase.sample
dictones/.git/hooks/pre-receive.sample
dictones/.git/hooks/prepare-commit-msg.sample
dictones/.git/hooks/push-to-checkout.sample
dictones/.git/hooks/update.sample
dictones/.git/index
dictones/.git/info/exclude
dictones/.git/logs/HEAD
dictones/.git/logs/refs/heads/master
dictones/.git/logs/refs/remotes/origin/master
dictones/.git/objects/09/1d07e9c7528dcf7761f1127f06582ac40236ab
dictones/.git/objects/16/7184c2d2fbddb555e65a0815e279b8c024954e
dictones/.git/objects/1a/85682771824160d9d84502396e87d8f194404d
dictones/.git/objects/2d/a5ac976b1554ee0df959fbc33495d4fdcdeacc
dictones/.git/objects/37/1b4907b131bda64921792c81bcd4e30e78ae6d
dictones/.git/objects/5f/9769004cea452f08a85a266fe3be7b79d0eff4
dictones/.git/objects/89/64be314c90fd75730c9cbb94ac32bdc75c4284
dictones/.git/objects/94/819c0d055d1e66382d686ccc7991f3bb261309
dictones/.git/objects/96/f5b13d16ddbf65b5c51642fbe934ec2328d6d1
dictones/.git/objects/aa/2539ec7fe8a1ff79a47b1f073bf9622d7fdd09
dictones/.git/objects/bf/c254d171d9763bb5900820d45f31fa46587634
dictones/.git/objects/e1/96388b395330d042e8899c67f9a940a207ba87
dictones/.git/objects/f6/a6dfbf666e9454b3b0980f8667b53c552a0dc5
dictones/.git/refs/heads/master
dictones/.git/refs/remotes/origin/master
dictones/.idea/.gitignore
dictones/.idea/inspectionProfiles/profiles_settings.xml
dictones/.idea/inspectionProfiles/Project_Default.xml
dictones/.idea/misc.xml
dictones/.idea/modules.xml
dictones/.idea/TableValue.iml
dictones/.idea/vcs.xml
dictones/.idea/workspace.xml
dictones/__init__.py
dictones/__init__.py.bak
dictones-0.1.1.dist-info/WHEEL
dictones-0.1.1.dist-info/METADATA
dictones-0.1.1.dist-info/RECORD
